MANIFEST.in
README.rst
setup.py
Products/__init__.py
Products.PloneSurvey.egg-info/PKG-INFO
Products.PloneSurvey.egg-info/SOURCES.txt
Products.PloneSurvey.egg-info/dependency_links.txt
Products.PloneSurvey.egg-info/entry_points.txt
Products.PloneSurvey.egg-info/namespace_packages.txt
Products.PloneSurvey.egg-info/not-zip-safe
Products.PloneSurvey.egg-info/requires.txt
Products.PloneSurvey.egg-info/top_level.txt
Products/PloneSurvey/__init__.py
Products/PloneSurvey/config.py
Products/PloneSurvey/configure.zcml
Products/PloneSurvey/isodatevalidator.py
Products/PloneSurvey/permissions.py
Products/PloneSurvey/permissions.zcml
Products/PloneSurvey/profiles.zcml
Products/PloneSurvey/setuphandlers.py
Products/PloneSurvey/version.txt
Products/PloneSurvey/browser/__init__.py
Products/PloneSurvey/browser/configure.zcml
Products/PloneSurvey/browser/folderfactories.pt
Products/PloneSurvey/browser/importer.py
Products/PloneSurvey/browser/interfaces.py
Products/PloneSurvey/browser/images/barchart_blue.gif
Products/PloneSurvey/browser/images/barchart_cyan.gif
Products/PloneSurvey/browser/images/barchart_green.gif
Products/PloneSurvey/browser/images/barchart_magneta.gif
Products/PloneSurvey/browser/images/barchart_red.gif
Products/PloneSurvey/browser/images/barchart_yellow.gif
Products/PloneSurvey/browser/images/icon_plonesurvey.gif
Products/PloneSurvey/browser/javascripts/survey_reset.js
Products/PloneSurvey/browser/questions/__init__.py
Products/PloneSurvey/browser/questions/configure.zcml
Products/PloneSurvey/browser/questions/question_date_macro.pt
Products/PloneSurvey/browser/questions/question_macro.pt
Products/PloneSurvey/browser/questions/question_matrix_macro.pt
Products/PloneSurvey/browser/questions/question_select_macro.pt
Products/PloneSurvey/browser/questions/survey_overview.pt
Products/PloneSurvey/browser/questions/survey_overview_macro.pt
Products/PloneSurvey/browser/results/__init__.py
Products/PloneSurvey/browser/results/comments_view.pt
Products/PloneSurvey/browser/results/configure.zcml
Products/PloneSurvey/browser/results/html_spreadsheet.pt
Products/PloneSurvey/browser/results/question_barchart.pt
Products/PloneSurvey/browser/results/respondents_table.pt
Products/PloneSurvey/browser/results/respondents_table.py
Products/PloneSurvey/browser/results/survey_barchart.pt
