Metadata-Version: 1.1
Name: Products.PloneSurvey
Version: 1.4.10
Summary: Plone Survey is an addon collecting data from people.
Home-page: http://plone.org/products/plonesurvey
Author: Michael Davis
Author-email: m.r.davis@me.com
License: GPL
Keywords: Plone,Survey
Platform: UNKNOWN
Classifier: Framework :: Plone
Classifier: Framework :: Plone :: 4.3
Classifier: Programming Language :: Python
Classifier: Topic :: Software Development :: Libraries :: Python Modules
